LICENSE.txt
README.md
setup.py
e2e_gpu/__init__.py
e2e_gpu/commands_routing.py
e2e_gpu/e2e_parser.py
e2e_gpu/main.py
e2e_gpu/config/__init__.py
e2e_gpu/config/config.py
e2e_gpu/config/config_parser.py
e2e_gpu/config/config_routing.py
e2e_gpu/config/constants.py
e2e_gpu/core/__init__.py
e2e_gpu/core/cli_helpers.py
e2e_gpu/core/config_service.py
e2e_gpu/core/constants.py
e2e_gpu/core/request_service.py
e2e_gpu/tir/__init__.py
e2e_gpu/tir/endpoints.py
e2e_gpu/tir/pipelines.py
e2e_gpu/tir/projects.py
e2e_gpu/tir/teams.py
e2e_gpu/tir/datasets/__init__.py
e2e_gpu/tir/datasets/constants.py
e2e_gpu/tir/datasets/dataset_parser.py
e2e_gpu/tir/datasets/dataset_routing.py
e2e_gpu/tir/datasets/datasets.py
e2e_gpu/tir/datasets/validators.py
e2e_gpu/tir/images/__init__.py
e2e_gpu/tir/images/image_parser.py
e2e_gpu/tir/images/image_routing.py
e2e_gpu/tir/images/images.py
e2e_gpu/tir/inference/__init__.py
e2e_gpu/tir/inference/constants.py
e2e_gpu/tir/inference/notebook_parser.py
e2e_gpu/tir/inference/notebook_routing.py
e2e_gpu/tir/inference/notebooks.py
e2e_gpu/tir/inference/validators.py
e2e_gpu/tir/models/__init__.py
e2e_gpu/tir/models/constants.py
e2e_gpu/tir/models/model_parser.py
e2e_gpu/tir/models/model_routing.py
e2e_gpu/tir/models/models.py
e2e_gpu/tir/models/validators.py
e2e_gpu/tir/notebooks/__init__.py
e2e_gpu/tir/notebooks/constants.py
e2e_gpu/tir/notebooks/notebook_parser.py
e2e_gpu/tir/notebooks/notebook_routing.py
e2e_gpu/tir/notebooks/notebooks.py
e2e_gpu/tir/notebooks/validators.py
e2e_gpu/tir/plans/__init__.py
e2e_gpu/tir/plans/plan_parser.py
e2e_gpu/tir/plans/plan_routing.py
e2e_gpu/tir/plans/plans.py
tir_cli.egg-info/PKG-INFO
tir_cli.egg-info/SOURCES.txt
tir_cli.egg-info/dependency_links.txt
tir_cli.egg-info/entry_points.txt
tir_cli.egg-info/requires.txt
tir_cli.egg-info/top_level.txt