Metadata-Version: 2.1
Name: tir-cli
Version: 0.1.1
Summary: This a E2E CLI tool for TIR AI-ML
Author: Aman
License-File: LICENSE.txt
